{
  "products": [
    {
      "title": "messi",
      "description": "barca",
      "price": 70000,
      "image": "https://www.sport.ru/ai/files/tags_attrs/r63/9e42b41b6000.jpg",
      "id": 1
    },
    {
      "title": "Toyota Camry",
      "description": "75",
      "price": 50000,
      "image": "https://osnova.news/i/n/9589/13799836.jpg",
      "id": 2
    },
    {
      "title": "Mercedes Gelenvagen",
      "description": "mers",
      "price": 60000,
      "image": "https://carakoom.com/data/wall/787/6434237a_medium.jpg",
      "id": 3
    },
    {
      "title": "Toyota Alphard",
      "description": "restailing",
      "price": 60000,
      "image": "https://weststarmotors.com.my/wp-content/uploads/2021/08/Front-1-5.jpg",
      "id": 4
    },
    {
      "title": "lkjsdflc;ajd",
      "description": "slkdjfipehrp",
      "price": 876976486537,
      "image": "wdfljow[dijri[v",
      "id": 5
    },
    {
      "title": "Toyota Crown",
      "description": "Hybrid 2.5",
      "price": 23000,
      "image": "https://i.i-sgcm.com/cars_used/202105/998441_2b.jpg",
      "id": 6
    },
    {
      "title": "Toyota Caldina",
      "description": "2.0",
      "price": 7000,
      "image": "https://upload.wikimedia.org/wikipedia/commons/thumb/2/22/2002-2004_Toyota_Caldina_GT-FOUR.jpg/800px-2002-2004_Toyota_Caldina_GT-FOUR.jpg",
      "id": 7
    }
  ]
}